FEMSections/__init__.py
FEMSections/FEM1D/Elemento.py
FEMSections/FEM1D/FEMSections.py
FEMSections/FEM1D/__init__.py
FEMSections/FEM2D/CuadrilateroL.py
FEMSections/FEM2D/Elasticidad.py
FEMSections/FEM2D/Elemento.py
FEMSections/FEM2D/FEM.py
FEMSections/FEM2D/FEM1V.py
FEMSections/FEM2D/SerendipityC.py
FEMSections/FEM2D/TriangularC.py
FEMSections/FEM2D/TriangularL.py
FEMSections/FEM2D/__init__.py
FEMSections/FEM2D/integradorRectangular.py
FEMSections/FEM2D/integradorTriangular.py
FEMSections/FEM2D/Mesh/__init__.py
FEMSections/FEM2D/Mesh/delaunay.py
FEMSections/FEM2D/Utils/FEM1V.py
FEMSections/FEM2D/Utils/__init__.py
FEMSections/FEM2D/Utils/error.py
FEMSections/FEM2D/Utils/polygonal.py
FEMSections-1.1.1.dist-info/LICENSE
FEMSections-1.1.1.dist-info/METADATA
FEMSections-1.1.1.dist-info/WHEEL
FEMSections-1.1.1.dist-info/top_level.txt
FEMSections-1.1.1.dist-info/RECORD
