Metadata-Version: 2.1
Name: FEMSections
Version: 1.1.1
Summary: Finite Element Method (FEM) in Python
Home-page: https://github.com/ZibraMax/FEMSections
Author: Arturo Rodriguez
Author-email: davidarturo9911@hotmail.com
License: UNKNOWN
Platform: UNKNOWN
Classifier: Programming Language :: Python :: 3
Classifier: License :: OSI Approved :: MIT License
Classifier: Operating System :: OS Independent
Requires-Python: >=3.6
Requires-Dist: matplotlib
Requires-Dist: numpy
Requires-Dist: triangle
Requires-Dist: IPython
